{"GlobalPropertiesHash":"I0TTspa+e14YPC0q/lcQZgFGBye0TdqOm7MkYGjedFo=","FingerprintPatternsHash":"gq3WsqcKBUGTSNle7RKKyXRIwh7M8ccEqOqYvIzoM04=","PropertyOverridesHash":"8ZRc1sGeVrPBx4lD717BgRaQekyh78QKV9SKsdt638U=","InputHashes":["tpZ4Yj487M8VIvIwLnSDQ8OrKPJPKKKKjf46aS7IwSc=","0uwr77WM/ArmPJUtqvR9L3pDCSmPpC75jjiLP2ty\u002Bqo=","8rfIH93v9C2CGVzErhHdfXUlVzq1d2rdiaI9XfNVTp4="],"CachedAssets":{"tpZ4Yj487M8VIvIwLnSDQ8OrKPJPKKKKjf46aS7IwSc=":{"Identity":"X:\\sadasdasdasd\\ITBus\\ITBus\\wwwroot\\index.html","SourceId":"ITBus","SourceType":"Discovered","ContentRoot":"X:\\sadasdasdasd\\ITBus\\ITBus\\wwwroot\\","BasePath":"/","RelativePath":"index#[.{fingerprint}]?.html","AssetKind":"All","AssetMode":"All","AssetRole":"Primary","AssetMergeBehavior":null,"AssetMergeSource":"","RelatedAsset":null,"AssetTraitName":null,"AssetTraitValue":null,"Fingerprint":"3stq7rwud0","Integrity":"vbOfv5tHsc\u002B/qzwkDQkdhWfR/rtVhBA4k1AmrBQuKFY=","CopyToOutputDirectory":"Never","CopyToPublishDirectory":"PreserveNewest","OriginalItemSpec":"wwwroot\\index.html","FileLength":2143,"LastWriteTime":"2025-12-16T23:46:01.9736363+00:00"}},"CachedCopyCandidates":{}}